.flake8
.gitignore
README.md
pytest.ini
requirements.txt
setup.py
tox.ini
.circleci/config.yml
src/__init__.py
src/find_unused_components.py
tests/test_camel_case_convertion.py
tests/test_count_imports_usage.py
tests/fixtures/Component.vue
unused_vue_components.egg-info/PKG-INFO
unused_vue_components.egg-info/SOURCES.txt
unused_vue_components.egg-info/dependency_links.txt
unused_vue_components.egg-info/not-zip-safe
unused_vue_components.egg-info/top_level.txt