Metadata-Version: 2.1
Name: unused-vue-components
Version: 0.1.0
Summary: Find unused vue components
Home-page: https://github.com/heaviss/unused-vue-components
Author: Vladimir Seregin
Author-email: 31631@rambler.ru
License: MIT
Platform: UNKNOWN
Classifier: Programming Language :: Python :: 2.7
Classifier: Programming Language :: Python :: 3
Classifier: License :: OSI Approved :: MIT License
Classifier: Operating System :: OS Independent
